sphinxawesome_safenet_theme/README.rst
sphinxawesome_safenet_theme/__init__.py
sphinxawesome_safenet_theme/admonition_ids.py
sphinxawesome_safenet_theme/breadcrumbs.html
sphinxawesome_safenet_theme/buttons.html
sphinxawesome_safenet_theme/footer.html
sphinxawesome_safenet_theme/header.html
sphinxawesome_safenet_theme/highlighting.py
sphinxawesome_safenet_theme/html_translator.py
sphinxawesome_safenet_theme/icons.py
sphinxawesome_safenet_theme/jinja_filters.py
sphinxawesome_safenet_theme/layout.html
sphinxawesome_safenet_theme/menu.html
sphinxawesome_safenet_theme/modals.html
sphinxawesome_safenet_theme/permalinks_backport.py
sphinxawesome_safenet_theme/postprocess.py
sphinxawesome_safenet_theme/prev_next.html
sphinxawesome_safenet_theme/search-pane.html
sphinxawesome_safenet_theme/search.html
sphinxawesome_safenet_theme/sidebar.html
sphinxawesome_safenet_theme/skip.html
sphinxawesome_safenet_theme/static/0d8bb5b3ee5f5dac9e446d48480d28a9.woff2
sphinxawesome_safenet_theme/static/176f8f5bd5f02b3abfcf894955d7e919.woff2
sphinxawesome_safenet_theme/static/18d00f739ff1e1c52db1a1c0d9e98129.woff
sphinxawesome_safenet_theme/static/1c2e1cdea02e7dfab25424e6e42d7973.woff2
sphinxawesome_safenet_theme/static/1ed72cb00dc79e545eb2f86b41a14560.woff
sphinxawesome_safenet_theme/static/38b17c60ba71b3aa71c29b0493e6607d.woff
sphinxawesome_safenet_theme/static/49ae34d4cc6b98c00c69ab4c41de3e0c.woff
sphinxawesome_safenet_theme/static/4a0ed4c488992e375e9793218146647b.woff
sphinxawesome_safenet_theme/static/647f3654373165e51135a4fddf0006a9.woff2
sphinxawesome_safenet_theme/static/b1d9d9904bfca8802a631c45590b9efa.woff
sphinxawesome_safenet_theme/static/cba8e90503370863b3a0036bda7b0e44.woff
sphinxawesome_safenet_theme/static/cea99d3e3e13a3a599a015c29f1046d0.woff
sphinxawesome_safenet_theme/static/d022bc70dc1bf7b3425da9cdaa9841b6.woff2
sphinxawesome_safenet_theme/static/d4e12e8e9e242435ab9cbd5a2086ca2c.woff2
sphinxawesome_safenet_theme/static/f5b74d7ffcdf85b9dd60130fa0b2c087.woff2
sphinxawesome_safenet_theme-0.0.2.dist-info/entry_points.txt
sphinxawesome_safenet_theme-0.0.2.dist-info/LICENSE
sphinxawesome_safenet_theme-0.0.2.dist-info/WHEEL
sphinxawesome_safenet_theme-0.0.2.dist-info/METADATA
sphinxawesome_safenet_theme-0.0.2.dist-info/RECORD
