Metadata-Version: 2.1
Name: sphinxawesome-safenet-theme
Version: 0.0.2
Summary: A Thales community doc theme based on sphinxawesome-theme
Home-page: https://github.com/kai687/sphinxawesome-theme
License: MIT
Author: Kai Welke
Author-email: kai687@pm.me
Requires-Python: >=3.6.1,<4.0.0
Classifier: Framework :: Sphinx
Classifier: Framework :: Sphinx :: Theme
Classifier: License :: OSI Approved :: MIT License
Classifier: Programming Language :: Python
Classifier: Programming Language :: Python :: 3
Classifier: Programming Language :: Python :: 3.7
Classifier: Programming Language :: Python :: 3.8
Classifier: Programming Language :: Python :: 3.9
Classifier: Topic :: Documentation
Classifier: Topic :: Documentation :: Sphinx
Classifier: Topic :: Software Development :: Documentation
Requires-Dist: beautifulsoup4 (>=4.9.1,<5.0.0)
Requires-Dist: importlib_metadata (>=1.6.1,<3.0.0); python_version < "3.8"
Requires-Dist: sphinx (>3)
Requires-Dist: sphinxawesome-sampdirective (>=1.0.3,<2.0.0)
Project-URL: Repository, https://github.com/kai687/sphinxawesome-theme
